dataset_interfaces/__init__.py
dataset_interfaces/generate.py
dataset_interfaces/imagenet_utils.py
dataset_interfaces/inference_utils.py
dataset_interfaces/templates.py
dataset_interfaces/textual_inversion.py
dataset_interfaces/utils.py
dataset_interfaces-0.1.0.dist-info/LICENSE
dataset_interfaces-0.1.0.dist-info/METADATA
dataset_interfaces-0.1.0.dist-info/WHEEL
dataset_interfaces-0.1.0.dist-info/top_level.txt
dataset_interfaces-0.1.0.dist-info/RECORD
