Metadata-Version: 2.1
Name: dataset-interfaces
Version: 0.1.0
Summary: Dataset Interfaces
Home-page: https://github.com/MadryLab/dataset-interfaces
Author: MadryLab
Author-email: jvendrow@mit.edu
License: MIT
License-File: LICENSE
Requires-Dist: torch
Requires-Dist: numpy
Requires-Dist: torchvision
Requires-Dist: diffusers
Requires-Dist: transformers
Requires-Dist: accelerate
